module_collecter/__init__.py
module_collecter/cli.py
module_collecter/core.py
module_collecter/models.py
module_collecter/py.typed
module_collecter-0.0.1.dist-info/entry_points.txt
module_collecter-0.0.1.dist-info/LICENSE
module_collecter-0.0.1.dist-info/METADATA
module_collecter-0.0.1.dist-info/WHEEL
module_collecter-0.0.1.dist-info/RECORD
