Metadata-Version: 2.1
Name: module-collecter
Version: 0.0.1
Summary: Collect submodules from a package.
Home-page: https://github.com/DinhHuy2010/module-collecter
License: MIT
Author: DinhHuy2010
Author-email: huy04052010@outlook.com
Requires-Python: >=3.9,<4.0
Classifier: License :: OSI Approved :: MIT License
Classifier: Programming Language :: Python :: 3
Classifier: Programming Language :: Python :: 3.9
Classifier: Programming Language :: Python :: 3.10
Classifier: Programming Language :: Python :: 3.11
Classifier: Programming Language :: Python :: 3.12
Requires-Dist: attrs (>=23.2.0,<24.0.0)
Requires-Dist: click (>=8.1.7,<9.0.0)
